alacomba_multiply/__init__.py
alacomba_multiply/multiplication.py
alacomba_multiply-0.1.0.dist-info/METADATA
alacomba_multiply-0.1.0.dist-info/WHEEL
alacomba_multiply-0.1.0.dist-info/top_level.txt
alacomba_multiply-0.1.0.dist-info/RECORD
